{
  "uid": "alo-usage",
  "title": "ALO \u2014 Cluster Usage",
  "description": "Request rates, latency percentiles, error tracking, and data volume analytics.",
  "tags": [
    "alo",
    "observability"
  ],
  "timezone": "browser",
  "schemaVersion": 39,
  "version": 1,
  "refresh": "30s",
  "time": {
    "from": "now-15m",
    "to": "now"
  },
  "panels": [
    {
      "id": 1,
      "title": "Request Rates",
      "type": "text",
      "gridPos": {
        "x": 0,
        "y": 0,
        "w": 24,
        "h": 2
      },
      "fieldConfig": {
        "defaults": {},
        "overrides": []
      },
      "options": {
        "mode": "markdown",
        "content": "### Request Rates"
      }
    },
    {
      "id": 2,
      "title": "Total Request Rate",
      "type": "timeseries",
      "datasource": {
        "type": "grafana-clickhouse-datasource",
        "uid": "${datasource}"
      },
      "gridPos": {
        "x": 0,
        "y": 2,
        "w": 24,
        "h": 8
      },
      "description": "Total request count over time across the selected filters.",
      "targets": [
        {
          "datasource": {
            "type": "grafana-clickhouse-datasource",
            "uid": "${datasource}"
          },
          "refId": "A",
          "editorType": "sql",
          "queryType": "timeseries",
          "format": 1,
          "rawSql": "SELECT $__timeInterval(timestamp) AS t, count() AS value FROM alo.alo_raw WHERE $__timeFilter(timestamp) AND (('${cluster:csv}' = '*') OR cluster_name IN (${cluster:singlequote})) AND (('${application:csv}' = '*') OR identity_applicative_provider IN (${application:singlequote})) AND (('${target:csv}' = '*') OR request_target IN (${target:singlequote})) AND (('${operation:csv}' = '*') OR request_operation IN (${operation:singlequote})) AND (('${username:csv}' = '*') OR identity_username IN (${username:singlequote})) AND (('${cost_indicator:csv}' = '*') OR hasAny(stress_cost_indicator_names, [${cost_indicator:singlequote}])) AND (('${client_host:csv}' = '*') OR identity_client_host IN (${client_host:singlequote})) AND (('${template:csv}' = '*') OR request_template IN (${template:singlequote})) GROUP BY t ORDER BY t",
          "meta": {
            "builderOptions": {}
          },
          "alias": "Requests"
        }
      ],
      "options": {
        "legend": {
          "displayMode": "list",
          "placement": "right"
        },
        "tooltip": {
          "mode": "multi"
        }
      },
      "fieldConfig": {
        "defaults": {
          "custom": {
            "drawStyle": "line",
            "fillOpacity": 0
          }
        },
        "overrides": []
      }
    },
    {
      "id": 3,
      "title": "Rate by Operation",
      "type": "timeseries",
      "datasource": {
        "type": "grafana-clickhouse-datasource",
        "uid": "${datasource}"
      },
      "gridPos": {
        "x": 0,
        "y": 10,
        "w": 24,
        "h": 8
      },
      "description": "Request rate over time, broken down by operation. Dashed series = hourly summary-index fallback (survives raw-data ILM expiry).",
      "targets": [
        {
          "datasource": {
            "type": "grafana-clickhouse-datasource",
            "uid": "${datasource}"
          },
          "refId": "A",
          "editorType": "sql",
          "queryType": "timeseries",
          "format": 1,
          "rawSql": "SELECT $__timeInterval(timestamp) AS t, request_operation AS series, count() AS value FROM alo.alo_raw WHERE $__timeFilter(timestamp) AND (('${cluster:csv}' = '*') OR cluster_name IN (${cluster:singlequote})) AND (('${application:csv}' = '*') OR identity_applicative_provider IN (${application:singlequote})) AND (('${target:csv}' = '*') OR request_target IN (${target:singlequote})) AND (('${operation:csv}' = '*') OR request_operation IN (${operation:singlequote})) AND (('${username:csv}' = '*') OR identity_username IN (${username:singlequote})) AND (('${cost_indicator:csv}' = '*') OR hasAny(stress_cost_indicator_names, [${cost_indicator:singlequote}])) AND (('${client_host:csv}' = '*') OR identity_client_host IN (${client_host:singlequote})) AND (('${template:csv}' = '*') OR request_template IN (${template:singlequote}))   AND request_operation IN (    SELECT request_operation FROM alo.alo_raw     WHERE $__timeFilter(timestamp) AND (('${cluster:csv}' = '*') OR cluster_name IN (${cluster:singlequote})) AND (('${application:csv}' = '*') OR identity_applicative_provider IN (${application:singlequote})) AND (('${target:csv}' = '*') OR request_target IN (${target:singlequote})) AND (('${operation:csv}' = '*') OR request_operation IN (${operation:singlequote})) AND (('${username:csv}' = '*') OR identity_username IN (${username:singlequote})) AND (('${cost_indicator:csv}' = '*') OR hasAny(stress_cost_indicator_names, [${cost_indicator:singlequote}])) AND (('${client_host:csv}' = '*') OR identity_client_host IN (${client_host:singlequote})) AND (('${template:csv}' = '*') OR request_template IN (${template:singlequote}))     GROUP BY request_operation ORDER BY count() DESC LIMIT 8  ) GROUP BY t, series ORDER BY t",
          "meta": {
            "builderOptions": {}
          }
        },
        {
          "datasource": {
            "type": "grafana-clickhouse-datasource",
            "uid": "${datasource}"
          },
          "refId": "B",
          "editorType": "sql",
          "queryType": "timeseries",
          "format": 1,
          "rawSql": "SELECT toStartOfHour(time_bucket) AS t, request_operation AS series, countMerge(count_state) AS value FROM alo.alo_summary WHERE $__timeFilter(time_bucket) AND (('${cluster:csv}' = '*') OR cluster_name IN (${cluster:singlequote})) AND (('${application:csv}' = '*') OR identity_applicative_provider IN (${application:singlequote})) AND (('${target:csv}' = '*') OR request_target IN (${target:singlequote})) AND (('${operation:csv}' = '*') OR request_operation IN (${operation:singlequote})) AND (('${username:csv}' = '*') OR identity_username IN (${username:singlequote})) AND (('${cost_indicator:csv}' = '*') OR hasAny(stress_cost_indicator_names, [${cost_indicator:singlequote}])) AND (('${client_host:csv}' = '*') OR identity_client_host IN (${client_host:singlequote})) AND (('${template:csv}' = '*') OR request_template IN (${template:singlequote})) GROUP BY t, series ORDER BY t LIMIT 8 BY t",
          "meta": {
            "builderOptions": {}
          }
        }
      ],
      "options": {
        "legend": {
          "displayMode": "list",
          "placement": "right"
        },
        "tooltip": {
          "mode": "multi"
        }
      },
      "fieldConfig": {
        "defaults": {
          "custom": {
            "drawStyle": "line",
            "fillOpacity": 20
          }
        },
        "overrides": [
          {
            "matcher": {
              "id": "byFrameRefID",
              "options": "B"
            },
            "properties": [
              {
                "id": "custom.lineStyle",
                "value": {
                  "fill": "dash",
                  "dash": [
                    10,
                    10
                  ]
                }
              },
              {
                "id": "custom.lineWidth",
                "value": 1
              }
            ]
          }
        ]
      }
    },
    {
      "id": 4,
      "title": "Rate by Application",
      "type": "timeseries",
      "datasource": {
        "type": "grafana-clickhouse-datasource",
        "uid": "${datasource}"
      },
      "gridPos": {
        "x": 0,
        "y": 18,
        "w": 24,
        "h": 8
      },
      "description": "Request rate over time, broken down by application. Dashed series = hourly summary-index fallback (survives raw-data ILM expiry).",
      "targets": [
        {
          "datasource": {
            "type": "grafana-clickhouse-datasource",
            "uid": "${datasource}"
          },
          "refId": "A",
          "editorType": "sql",
          "queryType": "timeseries",
          "format": 1,
          "rawSql": "SELECT $__timeInterval(timestamp) AS t, identity_applicative_provider AS series, count() AS value FROM alo.alo_raw WHERE $__timeFilter(timestamp) AND (('${cluster:csv}' = '*') OR cluster_name IN (${cluster:singlequote})) AND (('${application:csv}' = '*') OR identity_applicative_provider IN (${application:singlequote})) AND (('${target:csv}' = '*') OR request_target IN (${target:singlequote})) AND (('${operation:csv}' = '*') OR request_operation IN (${operation:singlequote})) AND (('${username:csv}' = '*') OR identity_username IN (${username:singlequote})) AND (('${cost_indicator:csv}' = '*') OR hasAny(stress_cost_indicator_names, [${cost_indicator:singlequote}])) AND (('${client_host:csv}' = '*') OR identity_client_host IN (${client_host:singlequote})) AND (('${template:csv}' = '*') OR request_template IN (${template:singlequote}))   AND identity_applicative_provider IN (    SELECT identity_applicative_provider FROM alo.alo_raw     WHERE $__timeFilter(timestamp) AND (('${cluster:csv}' = '*') OR cluster_name IN (${cluster:singlequote})) AND (('${application:csv}' = '*') OR identity_applicative_provider IN (${application:singlequote})) AND (('${target:csv}' = '*') OR request_target IN (${target:singlequote})) AND (('${operation:csv}' = '*') OR request_operation IN (${operation:singlequote})) AND (('${username:csv}' = '*') OR identity_username IN (${username:singlequote})) AND (('${cost_indicator:csv}' = '*') OR hasAny(stress_cost_indicator_names, [${cost_indicator:singlequote}])) AND (('${client_host:csv}' = '*') OR identity_client_host IN (${client_host:singlequote})) AND (('${template:csv}' = '*') OR request_template IN (${template:singlequote}))     GROUP BY identity_applicative_provider ORDER BY count() DESC LIMIT 8  ) GROUP BY t, series ORDER BY t",
          "meta": {
            "builderOptions": {}
          }
        },
        {
          "datasource": {
            "type": "grafana-clickhouse-datasource",
            "uid": "${datasource}"
          },
          "refId": "B",
          "editorType": "sql",
          "queryType": "timeseries",
          "format": 1,
          "rawSql": "SELECT toStartOfHour(time_bucket) AS t, identity_applicative_provider AS series, countMerge(count_state) AS value FROM alo.alo_summary WHERE $__timeFilter(time_bucket) AND (('${cluster:csv}' = '*') OR cluster_name IN (${cluster:singlequote})) AND (('${application:csv}' = '*') OR identity_applicative_provider IN (${application:singlequote})) AND (('${target:csv}' = '*') OR request_target IN (${target:singlequote})) AND (('${operation:csv}' = '*') OR request_operation IN (${operation:singlequote})) AND (('${username:csv}' = '*') OR identity_username IN (${username:singlequote})) AND (('${cost_indicator:csv}' = '*') OR hasAny(stress_cost_indicator_names, [${cost_indicator:singlequote}])) AND (('${client_host:csv}' = '*') OR identity_client_host IN (${client_host:singlequote})) AND (('${template:csv}' = '*') OR request_template IN (${template:singlequote})) GROUP BY t, series ORDER BY t LIMIT 8 BY t",
          "meta": {
            "builderOptions": {}
          }
        }
      ],
      "options": {
        "legend": {
          "displayMode": "list",
          "placement": "right"
        },
        "tooltip": {
          "mode": "multi"
        }
      },
      "fieldConfig": {
        "defaults": {
          "custom": {
            "drawStyle": "line",
            "fillOpacity": 20
          }
        },
        "overrides": [
          {
            "matcher": {
              "id": "byFrameRefID",
              "options": "B"
            },
            "properties": [
              {
                "id": "custom.lineStyle",
                "value": {
                  "fill": "dash",
                  "dash": [
                    10,
                    10
                  ]
                }
              },
              {
                "id": "custom.lineWidth",
                "value": 1
              }
            ]
          }
        ]
      }
    },
    {
      "id": 5,
      "title": "Rate by Target Index",
      "type": "timeseries",
      "datasource": {
        "type": "grafana-clickhouse-datasource",
        "uid": "${datasource}"
      },
      "gridPos": {
        "x": 0,
        "y": 26,
        "w": 24,
        "h": 8
      },
      "description": "Request rate over time, broken down by target index. Dashed series = hourly summary-index fallback (survives raw-data ILM expiry).",
      "targets": [
        {
          "datasource": {
            "type": "grafana-clickhouse-datasource",
            "uid": "${datasource}"
          },
          "refId": "A",
          "editorType": "sql",
          "queryType": "timeseries",
          "format": 1,
          "rawSql": "SELECT $__timeInterval(timestamp) AS t, request_target AS series, count() AS value FROM alo.alo_raw WHERE $__timeFilter(timestamp) AND (('${cluster:csv}' = '*') OR cluster_name IN (${cluster:singlequote})) AND (('${application:csv}' = '*') OR identity_applicative_provider IN (${application:singlequote})) AND (('${target:csv}' = '*') OR request_target IN (${target:singlequote})) AND (('${operation:csv}' = '*') OR request_operation IN (${operation:singlequote})) AND (('${username:csv}' = '*') OR identity_username IN (${username:singlequote})) AND (('${cost_indicator:csv}' = '*') OR hasAny(stress_cost_indicator_names, [${cost_indicator:singlequote}])) AND (('${client_host:csv}' = '*') OR identity_client_host IN (${client_host:singlequote})) AND (('${template:csv}' = '*') OR request_template IN (${template:singlequote}))   AND request_target IN (    SELECT request_target FROM alo.alo_raw     WHERE $__timeFilter(timestamp) AND (('${cluster:csv}' = '*') OR cluster_name IN (${cluster:singlequote})) AND (('${application:csv}' = '*') OR identity_applicative_provider IN (${application:singlequote})) AND (('${target:csv}' = '*') OR request_target IN (${target:singlequote})) AND (('${operation:csv}' = '*') OR request_operation IN (${operation:singlequote})) AND (('${username:csv}' = '*') OR identity_username IN (${username:singlequote})) AND (('${cost_indicator:csv}' = '*') OR hasAny(stress_cost_indicator_names, [${cost_indicator:singlequote}])) AND (('${client_host:csv}' = '*') OR identity_client_host IN (${client_host:singlequote})) AND (('${template:csv}' = '*') OR request_template IN (${template:singlequote}))     GROUP BY request_target ORDER BY count() DESC LIMIT 8  ) GROUP BY t, series ORDER BY t",
          "meta": {
            "builderOptions": {}
          }
        },
        {
          "datasource": {
            "type": "grafana-clickhouse-datasource",
            "uid": "${datasource}"
          },
          "refId": "B",
          "editorType": "sql",
          "queryType": "timeseries",
          "format": 1,
          "rawSql": "SELECT toStartOfHour(time_bucket) AS t, request_target AS series, countMerge(count_state) AS value FROM alo.alo_summary WHERE $__timeFilter(time_bucket) AND (('${cluster:csv}' = '*') OR cluster_name IN (${cluster:singlequote})) AND (('${application:csv}' = '*') OR identity_applicative_provider IN (${application:singlequote})) AND (('${target:csv}' = '*') OR request_target IN (${target:singlequote})) AND (('${operation:csv}' = '*') OR request_operation IN (${operation:singlequote})) AND (('${username:csv}' = '*') OR identity_username IN (${username:singlequote})) AND (('${cost_indicator:csv}' = '*') OR hasAny(stress_cost_indicator_names, [${cost_indicator:singlequote}])) AND (('${client_host:csv}' = '*') OR identity_client_host IN (${client_host:singlequote})) AND (('${template:csv}' = '*') OR request_template IN (${template:singlequote})) GROUP BY t, series ORDER BY t LIMIT 8 BY t",
          "meta": {
            "builderOptions": {}
          }
        }
      ],
      "options": {
        "legend": {
          "displayMode": "list",
          "placement": "right"
        },
        "tooltip": {
          "mode": "multi"
        }
      },
      "fieldConfig": {
        "defaults": {
          "custom": {
            "drawStyle": "line",
            "fillOpacity": 20
          }
        },
        "overrides": [
          {
            "matcher": {
              "id": "byFrameRefID",
              "options": "B"
            },
            "properties": [
              {
                "id": "custom.lineStyle",
                "value": {
                  "fill": "dash",
                  "dash": [
                    10,
                    10
                  ]
                }
              },
              {
                "id": "custom.lineWidth",
                "value": 1
              }
            ]
          }
        ]
      }
    },
    {
      "id": 6,
      "title": "Rate by Template",
      "type": "timeseries",
      "datasource": {
        "type": "grafana-clickhouse-datasource",
        "uid": "${datasource}"
      },
      "gridPos": {
        "x": 0,
        "y": 34,
        "w": 24,
        "h": 8
      },
      "description": "Request rate over time, broken down by template. Dashed series = hourly summary-index fallback (survives raw-data ILM expiry).",
      "targets": [
        {
          "datasource": {
            "type": "grafana-clickhouse-datasource",
            "uid": "${datasource}"
          },
          "refId": "A",
          "editorType": "sql",
          "queryType": "timeseries",
          "format": 1,
          "rawSql": "SELECT $__timeInterval(timestamp) AS t, request_template AS series, count() AS value FROM alo.alo_raw WHERE $__timeFilter(timestamp) AND (('${cluster:csv}' = '*') OR cluster_name IN (${cluster:singlequote})) AND (('${application:csv}' = '*') OR identity_applicative_provider IN (${application:singlequote})) AND (('${target:csv}' = '*') OR request_target IN (${target:singlequote})) AND (('${operation:csv}' = '*') OR request_operation IN (${operation:singlequote})) AND (('${username:csv}' = '*') OR identity_username IN (${username:singlequote})) AND (('${cost_indicator:csv}' = '*') OR hasAny(stress_cost_indicator_names, [${cost_indicator:singlequote}])) AND (('${client_host:csv}' = '*') OR identity_client_host IN (${client_host:singlequote})) AND (('${template:csv}' = '*') OR request_template IN (${template:singlequote}))   AND request_template IN (    SELECT request_template FROM alo.alo_raw     WHERE $__timeFilter(timestamp) AND (('${cluster:csv}' = '*') OR cluster_name IN (${cluster:singlequote})) AND (('${application:csv}' = '*') OR identity_applicative_provider IN (${application:singlequote})) AND (('${target:csv}' = '*') OR request_target IN (${target:singlequote})) AND (('${operation:csv}' = '*') OR request_operation IN (${operation:singlequote})) AND (('${username:csv}' = '*') OR identity_username IN (${username:singlequote})) AND (('${cost_indicator:csv}' = '*') OR hasAny(stress_cost_indicator_names, [${cost_indicator:singlequote}])) AND (('${client_host:csv}' = '*') OR identity_client_host IN (${client_host:singlequote})) AND (('${template:csv}' = '*') OR request_template IN (${template:singlequote}))     GROUP BY request_template ORDER BY count() DESC LIMIT 8  ) GROUP BY t, series ORDER BY t",
          "meta": {
            "builderOptions": {}
          }
        },
        {
          "datasource": {
            "type": "grafana-clickhouse-datasource",
            "uid": "${datasource}"
          },
          "refId": "B",
          "editorType": "sql",
          "queryType": "timeseries",
          "format": 1,
          "rawSql": "SELECT toStartOfHour(time_bucket) AS t, request_template AS series, countMerge(count_state) AS value FROM alo.alo_summary WHERE $__timeFilter(time_bucket) AND (('${cluster:csv}' = '*') OR cluster_name IN (${cluster:singlequote})) AND (('${application:csv}' = '*') OR identity_applicative_provider IN (${application:singlequote})) AND (('${target:csv}' = '*') OR request_target IN (${target:singlequote})) AND (('${operation:csv}' = '*') OR request_operation IN (${operation:singlequote})) AND (('${username:csv}' = '*') OR identity_username IN (${username:singlequote})) AND (('${cost_indicator:csv}' = '*') OR hasAny(stress_cost_indicator_names, [${cost_indicator:singlequote}])) AND (('${client_host:csv}' = '*') OR identity_client_host IN (${client_host:singlequote})) AND (('${template:csv}' = '*') OR request_template IN (${template:singlequote})) GROUP BY t, series ORDER BY t LIMIT 8 BY t",
          "meta": {
            "builderOptions": {}
          }
        }
      ],
      "options": {
        "legend": {
          "displayMode": "list",
          "placement": "right"
        },
        "tooltip": {
          "mode": "multi"
        }
      },
      "fieldConfig": {
        "defaults": {
          "custom": {
            "drawStyle": "line",
            "fillOpacity": 20
          }
        },
        "overrides": [
          {
            "matcher": {
              "id": "byFrameRefID",
              "options": "B"
            },
            "properties": [
              {
                "id": "custom.lineStyle",
                "value": {
                  "fill": "dash",
                  "dash": [
                    10,
                    10
                  ]
                }
              },
              {
                "id": "custom.lineWidth",
                "value": 1
              }
            ]
          }
        ]
      }
    },
    {
      "id": 7,
      "title": "Latency",
      "type": "text",
      "gridPos": {
        "x": 0,
        "y": 42,
        "w": 24,
        "h": 2
      },
      "fieldConfig": {
        "defaults": {},
        "overrides": []
      },
      "options": {
        "mode": "markdown",
        "content": "### Latency"
      }
    },
    {
      "id": 8,
      "title": "ES Latency",
      "type": "timeseries",
      "datasource": {
        "type": "grafana-clickhouse-datasource",
        "uid": "${datasource}"
      },
      "gridPos": {
        "x": 0,
        "y": 44,
        "w": 24,
        "h": 8
      },
      "description": "Elasticsearch response-time trend with Avg / P50 / P95 / P99. Rising P95/P99 signals tail-latency issues.",
      "targets": [
        {
          "datasource": {
            "type": "grafana-clickhouse-datasource",
            "uid": "${datasource}"
          },
          "refId": "A",
          "editorType": "sql",
          "queryType": "timeseries",
          "format": 1,
          "rawSql": "SELECT $__timeInterval(timestamp) AS t, avg(response_es_took_ms) AS value FROM alo.alo_raw WHERE $__timeFilter(timestamp) AND (('${cluster:csv}' = '*') OR cluster_name IN (${cluster:singlequote})) AND (('${application:csv}' = '*') OR identity_applicative_provider IN (${application:singlequote})) AND (('${target:csv}' = '*') OR request_target IN (${target:singlequote})) AND (('${operation:csv}' = '*') OR request_operation IN (${operation:singlequote})) AND (('${username:csv}' = '*') OR identity_username IN (${username:singlequote})) AND (('${cost_indicator:csv}' = '*') OR hasAny(stress_cost_indicator_names, [${cost_indicator:singlequote}])) AND (('${client_host:csv}' = '*') OR identity_client_host IN (${client_host:singlequote})) AND (('${template:csv}' = '*') OR request_template IN (${template:singlequote})) GROUP BY t ORDER BY t",
          "meta": {
            "builderOptions": {}
          },
          "alias": "Avg"
        },
        {
          "datasource": {
            "type": "grafana-clickhouse-datasource",
            "uid": "${datasource}"
          },
          "refId": "B",
          "editorType": "sql",
          "queryType": "timeseries",
          "format": 1,
          "rawSql": "SELECT $__timeInterval(timestamp) AS t, quantile(0.5)(response_es_took_ms) AS value FROM alo.alo_raw WHERE $__timeFilter(timestamp) AND (('${cluster:csv}' = '*') OR cluster_name IN (${cluster:singlequote})) AND (('${application:csv}' = '*') OR identity_applicative_provider IN (${application:singlequote})) AND (('${target:csv}' = '*') OR request_target IN (${target:singlequote})) AND (('${operation:csv}' = '*') OR request_operation IN (${operation:singlequote})) AND (('${username:csv}' = '*') OR identity_username IN (${username:singlequote})) AND (('${cost_indicator:csv}' = '*') OR hasAny(stress_cost_indicator_names, [${cost_indicator:singlequote}])) AND (('${client_host:csv}' = '*') OR identity_client_host IN (${client_host:singlequote})) AND (('${template:csv}' = '*') OR request_template IN (${template:singlequote})) GROUP BY t ORDER BY t",
          "meta": {
            "builderOptions": {}
          },
          "alias": "P50"
        },
        {
          "datasource": {
            "type": "grafana-clickhouse-datasource",
            "uid": "${datasource}"
          },
          "refId": "C",
          "editorType": "sql",
          "queryType": "timeseries",
          "format": 1,
          "rawSql": "SELECT $__timeInterval(timestamp) AS t, quantile(0.95)(response_es_took_ms) AS value FROM alo.alo_raw WHERE $__timeFilter(timestamp) AND (('${cluster:csv}' = '*') OR cluster_name IN (${cluster:singlequote})) AND (('${application:csv}' = '*') OR identity_applicative_provider IN (${application:singlequote})) AND (('${target:csv}' = '*') OR request_target IN (${target:singlequote})) AND (('${operation:csv}' = '*') OR request_operation IN (${operation:singlequote})) AND (('${username:csv}' = '*') OR identity_username IN (${username:singlequote})) AND (('${cost_indicator:csv}' = '*') OR hasAny(stress_cost_indicator_names, [${cost_indicator:singlequote}])) AND (('${client_host:csv}' = '*') OR identity_client_host IN (${client_host:singlequote})) AND (('${template:csv}' = '*') OR request_template IN (${template:singlequote})) GROUP BY t ORDER BY t",
          "meta": {
            "builderOptions": {}
          },
          "alias": "P95"
        },
        {
          "datasource": {
            "type": "grafana-clickhouse-datasource",
            "uid": "${datasource}"
          },
          "refId": "D",
          "editorType": "sql",
          "queryType": "timeseries",
          "format": 1,
          "rawSql": "SELECT $__timeInterval(timestamp) AS t, quantile(0.99)(response_es_took_ms) AS value FROM alo.alo_raw WHERE $__timeFilter(timestamp) AND (('${cluster:csv}' = '*') OR cluster_name IN (${cluster:singlequote})) AND (('${application:csv}' = '*') OR identity_applicative_provider IN (${application:singlequote})) AND (('${target:csv}' = '*') OR request_target IN (${target:singlequote})) AND (('${operation:csv}' = '*') OR request_operation IN (${operation:singlequote})) AND (('${username:csv}' = '*') OR identity_username IN (${username:singlequote})) AND (('${cost_indicator:csv}' = '*') OR hasAny(stress_cost_indicator_names, [${cost_indicator:singlequote}])) AND (('${client_host:csv}' = '*') OR identity_client_host IN (${client_host:singlequote})) AND (('${template:csv}' = '*') OR request_template IN (${template:singlequote})) GROUP BY t ORDER BY t",
          "meta": {
            "builderOptions": {}
          },
          "alias": "P99"
        }
      ],
      "options": {
        "legend": {
          "displayMode": "list",
          "placement": "right"
        },
        "tooltip": {
          "mode": "multi"
        }
      },
      "fieldConfig": {
        "defaults": {
          "custom": {
            "drawStyle": "line",
            "fillOpacity": 0
          },
          "unit": "ms"
        },
        "overrides": []
      }
    },
    {
      "id": 9,
      "title": "Errors",
      "type": "text",
      "gridPos": {
        "x": 0,
        "y": 52,
        "w": 24,
        "h": 2
      },
      "fieldConfig": {
        "defaults": {},
        "overrides": []
      },
      "options": {
        "mode": "markdown",
        "content": "### Errors"
      }
    },
    {
      "id": 10,
      "title": "Error Rate",
      "type": "timeseries",
      "datasource": {
        "type": "grafana-clickhouse-datasource",
        "uid": "${datasource}"
      },
      "gridPos": {
        "x": 0,
        "y": 54,
        "w": 12,
        "h": 8
      },
      "description": "Count of error responses (status \u2265 400) vs total requests.",
      "targets": [
        {
          "datasource": {
            "type": "grafana-clickhouse-datasource",
            "uid": "${datasource}"
          },
          "refId": "A",
          "editorType": "sql",
          "queryType": "timeseries",
          "format": 1,
          "rawSql": "SELECT $__timeInterval(timestamp) AS t, count() AS value FROM alo.alo_raw WHERE $__timeFilter(timestamp) AND (('${cluster:csv}' = '*') OR cluster_name IN (${cluster:singlequote})) AND (('${application:csv}' = '*') OR identity_applicative_provider IN (${application:singlequote})) AND (('${target:csv}' = '*') OR request_target IN (${target:singlequote})) AND (('${operation:csv}' = '*') OR request_operation IN (${operation:singlequote})) AND (('${username:csv}' = '*') OR identity_username IN (${username:singlequote})) AND (('${cost_indicator:csv}' = '*') OR hasAny(stress_cost_indicator_names, [${cost_indicator:singlequote}])) AND (('${client_host:csv}' = '*') OR identity_client_host IN (${client_host:singlequote})) AND (('${template:csv}' = '*') OR request_template IN (${template:singlequote})) AND response_status >= 400 GROUP BY t ORDER BY t",
          "meta": {
            "builderOptions": {}
          },
          "alias": "Errors (4xx+5xx)"
        },
        {
          "datasource": {
            "type": "grafana-clickhouse-datasource",
            "uid": "${datasource}"
          },
          "refId": "B",
          "editorType": "sql",
          "queryType": "timeseries",
          "format": 1,
          "rawSql": "SELECT $__timeInterval(timestamp) AS t, count() AS value FROM alo.alo_raw WHERE $__timeFilter(timestamp) AND (('${cluster:csv}' = '*') OR cluster_name IN (${cluster:singlequote})) AND (('${application:csv}' = '*') OR identity_applicative_provider IN (${application:singlequote})) AND (('${target:csv}' = '*') OR request_target IN (${target:singlequote})) AND (('${operation:csv}' = '*') OR request_operation IN (${operation:singlequote})) AND (('${username:csv}' = '*') OR identity_username IN (${username:singlequote})) AND (('${cost_indicator:csv}' = '*') OR hasAny(stress_cost_indicator_names, [${cost_indicator:singlequote}])) AND (('${client_host:csv}' = '*') OR identity_client_host IN (${client_host:singlequote})) AND (('${template:csv}' = '*') OR request_template IN (${template:singlequote})) GROUP BY t ORDER BY t",
          "meta": {
            "builderOptions": {}
          },
          "alias": "Total Requests"
        }
      ],
      "options": {
        "legend": {
          "displayMode": "list",
          "placement": "right"
        },
        "tooltip": {
          "mode": "multi"
        }
      },
      "fieldConfig": {
        "defaults": {
          "custom": {
            "drawStyle": "line",
            "fillOpacity": 0
          }
        },
        "overrides": []
      }
    },
    {
      "id": 11,
      "title": "Requests by Status Code",
      "type": "table",
      "datasource": {
        "type": "grafana-clickhouse-datasource",
        "uid": "${datasource}"
      },
      "gridPos": {
        "x": 12,
        "y": 54,
        "w": 12,
        "h": 8
      },
      "description": "Top 10 response status codes by request count.",
      "targets": [
        {
          "datasource": {
            "type": "grafana-clickhouse-datasource",
            "uid": "${datasource}"
          },
          "refId": "A",
          "editorType": "sql",
          "queryType": "table",
          "format": 0,
          "rawSql": "SELECT response_status AS \"Status Code\", count() AS \"Requests\" FROM alo.alo_raw WHERE $__timeFilter(timestamp) AND (('${cluster:csv}' = '*') OR cluster_name IN (${cluster:singlequote})) AND (('${application:csv}' = '*') OR identity_applicative_provider IN (${application:singlequote})) AND (('${target:csv}' = '*') OR request_target IN (${target:singlequote})) AND (('${operation:csv}' = '*') OR request_operation IN (${operation:singlequote})) AND (('${username:csv}' = '*') OR identity_username IN (${username:singlequote})) AND (('${cost_indicator:csv}' = '*') OR hasAny(stress_cost_indicator_names, [${cost_indicator:singlequote}])) AND (('${client_host:csv}' = '*') OR identity_client_host IN (${client_host:singlequote})) AND (('${template:csv}' = '*') OR request_template IN (${template:singlequote})) GROUP BY \"Status Code\" ORDER BY \"Requests\" DESC LIMIT 10",
          "meta": {
            "builderOptions": {}
          }
        }
      ],
      "options": {
        "showHeader": true,
        "sortBy": [
          {
            "displayName": "Requests",
            "desc": true
          }
        ]
      },
      "fieldConfig": {
        "defaults": {},
        "overrides": []
      }
    },
    {
      "id": 12,
      "title": "Requests by Application",
      "type": "table",
      "datasource": {
        "type": "grafana-clickhouse-datasource",
        "uid": "${datasource}"
      },
      "gridPos": {
        "x": 0,
        "y": 62,
        "w": 24,
        "h": 8
      },
      "description": "Per-application request counts and ES latency percentiles.",
      "targets": [
        {
          "datasource": {
            "type": "grafana-clickhouse-datasource",
            "uid": "${datasource}"
          },
          "refId": "A",
          "editorType": "sql",
          "queryType": "table",
          "format": 0,
          "rawSql": "SELECT identity_applicative_provider AS \"Application\", count() AS \"Requests\", quantile(0.5)(response_es_took_ms) AS \"P50 ES Latency (ms)\", quantile(0.95)(response_es_took_ms) AS \"P95 ES Latency (ms)\", quantile(0.99)(response_es_took_ms) AS \"P99 ES Latency (ms)\" FROM alo.alo_raw WHERE $__timeFilter(timestamp) AND (('${cluster:csv}' = '*') OR cluster_name IN (${cluster:singlequote})) AND (('${application:csv}' = '*') OR identity_applicative_provider IN (${application:singlequote})) AND (('${target:csv}' = '*') OR request_target IN (${target:singlequote})) AND (('${operation:csv}' = '*') OR request_operation IN (${operation:singlequote})) AND (('${username:csv}' = '*') OR identity_username IN (${username:singlequote})) AND (('${cost_indicator:csv}' = '*') OR hasAny(stress_cost_indicator_names, [${cost_indicator:singlequote}])) AND (('${client_host:csv}' = '*') OR identity_client_host IN (${client_host:singlequote})) AND (('${template:csv}' = '*') OR request_template IN (${template:singlequote})) GROUP BY \"Application\" ORDER BY \"Requests\" DESC LIMIT 10",
          "meta": {
            "builderOptions": {}
          }
        }
      ],
      "options": {
        "showHeader": true,
        "sortBy": [
          {
            "displayName": "Requests",
            "desc": true
          }
        ]
      },
      "fieldConfig": {
        "defaults": {
          "links": [
            {
              "title": "Filter by ${__data.fields[0]}",
              "url": "/d/alo-main?${__url_time_range}&var-application=${__data.fields[0]}",
              "targetBlank": false
            }
          ]
        },
        "overrides": []
      }
    },
    {
      "id": 13,
      "title": "Data Volume",
      "type": "text",
      "gridPos": {
        "x": 0,
        "y": 70,
        "w": 24,
        "h": 2
      },
      "fieldConfig": {
        "defaults": {},
        "overrides": []
      },
      "options": {
        "mode": "markdown",
        "content": "### Data Volume"
      }
    },
    {
      "id": 14,
      "title": "Read Volume (Total Hits)",
      "type": "timeseries",
      "datasource": {
        "type": "grafana-clickhouse-datasource",
        "uid": "${datasource}"
      },
      "gridPos": {
        "x": 0,
        "y": 72,
        "w": 12,
        "h": 8
      },
      "description": "Total documents matched by queries, split by operation type.",
      "targets": [
        {
          "datasource": {
            "type": "grafana-clickhouse-datasource",
            "uid": "${datasource}"
          },
          "refId": "A",
          "editorType": "sql",
          "queryType": "timeseries",
          "format": 1,
          "rawSql": "SELECT $__timeInterval(timestamp) AS t, request_operation AS series, sum(response_hits) AS value FROM alo.alo_raw WHERE $__timeFilter(timestamp) AND (('${cluster:csv}' = '*') OR cluster_name IN (${cluster:singlequote})) AND (('${application:csv}' = '*') OR identity_applicative_provider IN (${application:singlequote})) AND (('${target:csv}' = '*') OR request_target IN (${target:singlequote})) AND (('${operation:csv}' = '*') OR request_operation IN (${operation:singlequote})) AND (('${username:csv}' = '*') OR identity_username IN (${username:singlequote})) AND (('${cost_indicator:csv}' = '*') OR hasAny(stress_cost_indicator_names, [${cost_indicator:singlequote}])) AND (('${client_host:csv}' = '*') OR identity_client_host IN (${client_host:singlequote})) AND (('${template:csv}' = '*') OR request_template IN (${template:singlequote}))   AND request_operation IN (    SELECT request_operation FROM alo.alo_raw     WHERE $__timeFilter(timestamp) AND (('${cluster:csv}' = '*') OR cluster_name IN (${cluster:singlequote})) AND (('${application:csv}' = '*') OR identity_applicative_provider IN (${application:singlequote})) AND (('${target:csv}' = '*') OR request_target IN (${target:singlequote})) AND (('${operation:csv}' = '*') OR request_operation IN (${operation:singlequote})) AND (('${username:csv}' = '*') OR identity_username IN (${username:singlequote})) AND (('${cost_indicator:csv}' = '*') OR hasAny(stress_cost_indicator_names, [${cost_indicator:singlequote}])) AND (('${client_host:csv}' = '*') OR identity_client_host IN (${client_host:singlequote})) AND (('${template:csv}' = '*') OR request_template IN (${template:singlequote}))     GROUP BY request_operation ORDER BY count() DESC LIMIT 8  ) GROUP BY t, series ORDER BY t",
          "meta": {
            "builderOptions": {}
          }
        }
      ],
      "options": {
        "legend": {
          "displayMode": "list",
          "placement": "right"
        },
        "tooltip": {
          "mode": "multi"
        }
      },
      "fieldConfig": {
        "defaults": {
          "custom": {
            "drawStyle": "line",
            "fillOpacity": 20
          }
        },
        "overrides": []
      }
    },
    {
      "id": 15,
      "title": "Write Volume (Docs Affected)",
      "type": "timeseries",
      "datasource": {
        "type": "grafana-clickhouse-datasource",
        "uid": "${datasource}"
      },
      "gridPos": {
        "x": 12,
        "y": 72,
        "w": 12,
        "h": 8
      },
      "description": "Total documents written (indexed / updated / deleted), split by operation type.",
      "targets": [
        {
          "datasource": {
            "type": "grafana-clickhouse-datasource",
            "uid": "${datasource}"
          },
          "refId": "A",
          "editorType": "sql",
          "queryType": "timeseries",
          "format": 1,
          "rawSql": "SELECT $__timeInterval(timestamp) AS t, request_operation AS series, sum(response_docs_affected) AS value FROM alo.alo_raw WHERE $__timeFilter(timestamp) AND (('${cluster:csv}' = '*') OR cluster_name IN (${cluster:singlequote})) AND (('${application:csv}' = '*') OR identity_applicative_provider IN (${application:singlequote})) AND (('${target:csv}' = '*') OR request_target IN (${target:singlequote})) AND (('${operation:csv}' = '*') OR request_operation IN (${operation:singlequote})) AND (('${username:csv}' = '*') OR identity_username IN (${username:singlequote})) AND (('${cost_indicator:csv}' = '*') OR hasAny(stress_cost_indicator_names, [${cost_indicator:singlequote}])) AND (('${client_host:csv}' = '*') OR identity_client_host IN (${client_host:singlequote})) AND (('${template:csv}' = '*') OR request_template IN (${template:singlequote}))   AND request_operation IN (    SELECT request_operation FROM alo.alo_raw     WHERE $__timeFilter(timestamp) AND (('${cluster:csv}' = '*') OR cluster_name IN (${cluster:singlequote})) AND (('${application:csv}' = '*') OR identity_applicative_provider IN (${application:singlequote})) AND (('${target:csv}' = '*') OR request_target IN (${target:singlequote})) AND (('${operation:csv}' = '*') OR request_operation IN (${operation:singlequote})) AND (('${username:csv}' = '*') OR identity_username IN (${username:singlequote})) AND (('${cost_indicator:csv}' = '*') OR hasAny(stress_cost_indicator_names, [${cost_indicator:singlequote}])) AND (('${client_host:csv}' = '*') OR identity_client_host IN (${client_host:singlequote})) AND (('${template:csv}' = '*') OR request_template IN (${template:singlequote}))     GROUP BY request_operation ORDER BY count() DESC LIMIT 8  ) GROUP BY t, series ORDER BY t",
          "meta": {
            "builderOptions": {}
          }
        }
      ],
      "options": {
        "legend": {
          "displayMode": "list",
          "placement": "right"
        },
        "tooltip": {
          "mode": "multi"
        }
      },
      "fieldConfig": {
        "defaults": {
          "custom": {
            "drawStyle": "line",
            "fillOpacity": 20
          }
        },
        "overrides": []
      }
    },
    {
      "id": 16,
      "title": "Payload Sizes",
      "type": "timeseries",
      "datasource": {
        "type": "grafana-clickhouse-datasource",
        "uid": "${datasource}"
      },
      "gridPos": {
        "x": 0,
        "y": 80,
        "w": 24,
        "h": 8
      },
      "description": "Average request and response payload sizes over time.",
      "targets": [
        {
          "datasource": {
            "type": "grafana-clickhouse-datasource",
            "uid": "${datasource}"
          },
          "refId": "A",
          "editorType": "sql",
          "queryType": "timeseries",
          "format": 1,
          "rawSql": "SELECT $__timeInterval(timestamp) AS t, avg(request_size_bytes) AS value FROM alo.alo_raw WHERE $__timeFilter(timestamp) AND (('${cluster:csv}' = '*') OR cluster_name IN (${cluster:singlequote})) AND (('${application:csv}' = '*') OR identity_applicative_provider IN (${application:singlequote})) AND (('${target:csv}' = '*') OR request_target IN (${target:singlequote})) AND (('${operation:csv}' = '*') OR request_operation IN (${operation:singlequote})) AND (('${username:csv}' = '*') OR identity_username IN (${username:singlequote})) AND (('${cost_indicator:csv}' = '*') OR hasAny(stress_cost_indicator_names, [${cost_indicator:singlequote}])) AND (('${client_host:csv}' = '*') OR identity_client_host IN (${client_host:singlequote})) AND (('${template:csv}' = '*') OR request_template IN (${template:singlequote})) GROUP BY t ORDER BY t",
          "meta": {
            "builderOptions": {}
          },
          "alias": "Avg Request Size"
        },
        {
          "datasource": {
            "type": "grafana-clickhouse-datasource",
            "uid": "${datasource}"
          },
          "refId": "B",
          "editorType": "sql",
          "queryType": "timeseries",
          "format": 1,
          "rawSql": "SELECT $__timeInterval(timestamp) AS t, avg(response_size_bytes) AS value FROM alo.alo_raw WHERE $__timeFilter(timestamp) AND (('${cluster:csv}' = '*') OR cluster_name IN (${cluster:singlequote})) AND (('${application:csv}' = '*') OR identity_applicative_provider IN (${application:singlequote})) AND (('${target:csv}' = '*') OR request_target IN (${target:singlequote})) AND (('${operation:csv}' = '*') OR request_operation IN (${operation:singlequote})) AND (('${username:csv}' = '*') OR identity_username IN (${username:singlequote})) AND (('${cost_indicator:csv}' = '*') OR hasAny(stress_cost_indicator_names, [${cost_indicator:singlequote}])) AND (('${client_host:csv}' = '*') OR identity_client_host IN (${client_host:singlequote})) AND (('${template:csv}' = '*') OR request_template IN (${template:singlequote})) GROUP BY t ORDER BY t",
          "meta": {
            "builderOptions": {}
          },
          "alias": "Avg Response Size"
        }
      ],
      "options": {
        "legend": {
          "displayMode": "list",
          "placement": "right"
        },
        "tooltip": {
          "mode": "multi"
        }
      },
      "fieldConfig": {
        "defaults": {
          "custom": {
            "drawStyle": "line",
            "fillOpacity": 0
          },
          "unit": "decbytes"
        },
        "overrides": []
      }
    },
    {
      "id": 17,
      "title": "Top Activity",
      "type": "text",
      "gridPos": {
        "x": 0,
        "y": 88,
        "w": 24,
        "h": 2
      },
      "fieldConfig": {
        "defaults": {},
        "overrides": []
      },
      "options": {
        "mode": "markdown",
        "content": "### Top Activity"
      }
    },
    {
      "id": 18,
      "title": "Top 10 Applications",
      "type": "barchart",
      "datasource": {
        "type": "grafana-clickhouse-datasource",
        "uid": "${datasource}"
      },
      "gridPos": {
        "x": 0,
        "y": 90,
        "w": 8,
        "h": 10
      },
      "description": "Top 10 applicative providers by request count.",
      "targets": [
        {
          "datasource": {
            "type": "grafana-clickhouse-datasource",
            "uid": "${datasource}"
          },
          "refId": "A",
          "editorType": "sql",
          "queryType": "table",
          "format": 0,
          "rawSql": "SELECT identity_applicative_provider AS bucket, count() AS value FROM alo.alo_raw WHERE $__timeFilter(timestamp) AND (('${cluster:csv}' = '*') OR cluster_name IN (${cluster:singlequote})) AND (('${application:csv}' = '*') OR identity_applicative_provider IN (${application:singlequote})) AND (('${target:csv}' = '*') OR request_target IN (${target:singlequote})) AND (('${operation:csv}' = '*') OR request_operation IN (${operation:singlequote})) AND (('${username:csv}' = '*') OR identity_username IN (${username:singlequote})) AND (('${cost_indicator:csv}' = '*') OR hasAny(stress_cost_indicator_names, [${cost_indicator:singlequote}])) AND (('${client_host:csv}' = '*') OR identity_client_host IN (${client_host:singlequote})) AND (('${template:csv}' = '*') OR request_template IN (${template:singlequote})) GROUP BY bucket ORDER BY value DESC LIMIT 10",
          "meta": {
            "builderOptions": {}
          }
        }
      ],
      "options": {
        "orientation": "horizontal",
        "showValue": "always",
        "legend": {
          "displayMode": "hidden"
        },
        "tooltip": {
          "mode": "single"
        }
      },
      "fieldConfig": {
        "defaults": {
          "links": [
            {
              "title": "Filter by ${__data.fields[0]}",
              "url": "/d/alo-main?${__url_time_range}&var-application=${__data.fields[0]}",
              "targetBlank": false
            }
          ]
        },
        "overrides": []
      }
    },
    {
      "id": 19,
      "title": "Top 10 Indices",
      "type": "barchart",
      "datasource": {
        "type": "grafana-clickhouse-datasource",
        "uid": "${datasource}"
      },
      "gridPos": {
        "x": 8,
        "y": 90,
        "w": 8,
        "h": 10
      },
      "description": "Top 10 target indices by request count.",
      "targets": [
        {
          "datasource": {
            "type": "grafana-clickhouse-datasource",
            "uid": "${datasource}"
          },
          "refId": "A",
          "editorType": "sql",
          "queryType": "table",
          "format": 0,
          "rawSql": "SELECT request_target AS bucket, count() AS value FROM alo.alo_raw WHERE $__timeFilter(timestamp) AND (('${cluster:csv}' = '*') OR cluster_name IN (${cluster:singlequote})) AND (('${application:csv}' = '*') OR identity_applicative_provider IN (${application:singlequote})) AND (('${target:csv}' = '*') OR request_target IN (${target:singlequote})) AND (('${operation:csv}' = '*') OR request_operation IN (${operation:singlequote})) AND (('${username:csv}' = '*') OR identity_username IN (${username:singlequote})) AND (('${cost_indicator:csv}' = '*') OR hasAny(stress_cost_indicator_names, [${cost_indicator:singlequote}])) AND (('${client_host:csv}' = '*') OR identity_client_host IN (${client_host:singlequote})) AND (('${template:csv}' = '*') OR request_template IN (${template:singlequote})) GROUP BY bucket ORDER BY value DESC LIMIT 10",
          "meta": {
            "builderOptions": {}
          }
        }
      ],
      "options": {
        "orientation": "horizontal",
        "showValue": "always",
        "legend": {
          "displayMode": "hidden"
        },
        "tooltip": {
          "mode": "single"
        }
      },
      "fieldConfig": {
        "defaults": {
          "links": [
            {
              "title": "Filter by ${__data.fields[0]}",
              "url": "/d/alo-main?${__url_time_range}&var-target=${__data.fields[0]}",
              "targetBlank": false
            }
          ]
        },
        "overrides": []
      }
    },
    {
      "id": 20,
      "title": "Top 10 Users",
      "type": "barchart",
      "datasource": {
        "type": "grafana-clickhouse-datasource",
        "uid": "${datasource}"
      },
      "gridPos": {
        "x": 16,
        "y": 90,
        "w": 8,
        "h": 10
      },
      "description": "Top 10 users by request count.",
      "targets": [
        {
          "datasource": {
            "type": "grafana-clickhouse-datasource",
            "uid": "${datasource}"
          },
          "refId": "A",
          "editorType": "sql",
          "queryType": "table",
          "format": 0,
          "rawSql": "SELECT identity_username AS bucket, count() AS value FROM alo.alo_raw WHERE $__timeFilter(timestamp) AND (('${cluster:csv}' = '*') OR cluster_name IN (${cluster:singlequote})) AND (('${application:csv}' = '*') OR identity_applicative_provider IN (${application:singlequote})) AND (('${target:csv}' = '*') OR request_target IN (${target:singlequote})) AND (('${operation:csv}' = '*') OR request_operation IN (${operation:singlequote})) AND (('${username:csv}' = '*') OR identity_username IN (${username:singlequote})) AND (('${cost_indicator:csv}' = '*') OR hasAny(stress_cost_indicator_names, [${cost_indicator:singlequote}])) AND (('${client_host:csv}' = '*') OR identity_client_host IN (${client_host:singlequote})) AND (('${template:csv}' = '*') OR request_template IN (${template:singlequote})) GROUP BY bucket ORDER BY value DESC LIMIT 10",
          "meta": {
            "builderOptions": {}
          }
        }
      ],
      "options": {
        "orientation": "horizontal",
        "showValue": "always",
        "legend": {
          "displayMode": "hidden"
        },
        "tooltip": {
          "mode": "single"
        }
      },
      "fieldConfig": {
        "defaults": {
          "links": [
            {
              "title": "Filter by ${__data.fields[0]}",
              "url": "/d/alo-main?${__url_time_range}&var-username=${__data.fields[0]}",
              "targetBlank": false
            }
          ]
        },
        "overrides": []
      }
    }
  ],
  "templating": {
    "list": [
      {
        "type": "datasource",
        "name": "datasource",
        "label": "ClickHouse",
        "query": "grafana-clickhouse-datasource",
        "current": {
          "text": "ClickHouse (ALO)",
          "value": "alo-clickhouse"
        },
        "regex": ""
      },
      {
        "type": "datasource",
        "name": "datasource_prometheus",
        "label": "Prometheus",
        "query": "prometheus",
        "current": {
          "text": "Prometheus (ALO)",
          "value": "alo-prometheus"
        },
        "regex": ""
      },
      {
        "type": "query",
        "name": "cluster",
        "label": "Cluster",
        "datasource": {
          "type": "grafana-clickhouse-datasource",
          "uid": "${datasource}"
        },
        "query": {
          "refId": "var",
          "rawSql": "SELECT DISTINCT cluster_name FROM alo.alo_raw WHERE $__timeFilter(timestamp) ORDER BY 1 LIMIT 1000",
          "editorType": "sql"
        },
        "includeAll": true,
        "allValue": "*",
        "multi": true,
        "sort": 1,
        "refresh": 2,
        "current": {
          "text": "All",
          "value": "$__all",
          "selected": true
        }
      },
      {
        "type": "query",
        "name": "application",
        "label": "Application",
        "datasource": {
          "type": "grafana-clickhouse-datasource",
          "uid": "${datasource}"
        },
        "query": {
          "refId": "var",
          "rawSql": "SELECT DISTINCT identity_applicative_provider FROM alo.alo_raw WHERE $__timeFilter(timestamp) ORDER BY 1 LIMIT 1000",
          "editorType": "sql"
        },
        "includeAll": true,
        "allValue": "*",
        "multi": true,
        "sort": 1,
        "refresh": 2,
        "current": {
          "text": "All",
          "value": "$__all",
          "selected": true
        }
      },
      {
        "type": "query",
        "name": "target",
        "label": "Target",
        "datasource": {
          "type": "grafana-clickhouse-datasource",
          "uid": "${datasource}"
        },
        "query": {
          "refId": "var",
          "rawSql": "SELECT DISTINCT request_target FROM alo.alo_raw WHERE $__timeFilter(timestamp) ORDER BY 1 LIMIT 1000",
          "editorType": "sql"
        },
        "includeAll": true,
        "allValue": "*",
        "multi": true,
        "sort": 1,
        "refresh": 2,
        "current": {
          "text": "All",
          "value": "$__all",
          "selected": true
        }
      },
      {
        "type": "query",
        "name": "operation",
        "label": "Operation",
        "datasource": {
          "type": "grafana-clickhouse-datasource",
          "uid": "${datasource}"
        },
        "query": {
          "refId": "var",
          "rawSql": "SELECT DISTINCT request_operation FROM alo.alo_raw WHERE $__timeFilter(timestamp) ORDER BY 1 LIMIT 1000",
          "editorType": "sql"
        },
        "includeAll": true,
        "allValue": "*",
        "multi": true,
        "sort": 1,
        "refresh": 2,
        "current": {
          "text": "All",
          "value": "$__all",
          "selected": true
        }
      },
      {
        "type": "query",
        "name": "username",
        "label": "Username",
        "datasource": {
          "type": "grafana-clickhouse-datasource",
          "uid": "${datasource}"
        },
        "query": {
          "refId": "var",
          "rawSql": "SELECT DISTINCT identity_username FROM alo.alo_raw WHERE $__timeFilter(timestamp) ORDER BY 1 LIMIT 1000",
          "editorType": "sql"
        },
        "includeAll": true,
        "allValue": "*",
        "multi": true,
        "sort": 1,
        "refresh": 2,
        "current": {
          "text": "All",
          "value": "$__all",
          "selected": true
        }
      },
      {
        "type": "query",
        "name": "cost_indicator",
        "label": "Cost Indicator",
        "datasource": {
          "type": "grafana-clickhouse-datasource",
          "uid": "${datasource}"
        },
        "query": {
          "refId": "var",
          "rawSql": "SELECT DISTINCT arrayJoin(stress_cost_indicator_names) FROM alo.alo_raw WHERE $__timeFilter(timestamp) ORDER BY 1 LIMIT 1000",
          "editorType": "sql"
        },
        "includeAll": true,
        "allValue": "*",
        "multi": true,
        "sort": 1,
        "refresh": 2,
        "current": {
          "text": "All",
          "value": "$__all",
          "selected": true
        }
      },
      {
        "type": "query",
        "name": "client_host",
        "label": "Client Host",
        "datasource": {
          "type": "grafana-clickhouse-datasource",
          "uid": "${datasource}"
        },
        "query": {
          "refId": "var",
          "rawSql": "SELECT DISTINCT identity_client_host FROM alo.alo_raw WHERE $__timeFilter(timestamp) ORDER BY 1 LIMIT 1000",
          "editorType": "sql"
        },
        "includeAll": true,
        "allValue": "*",
        "multi": true,
        "sort": 1,
        "refresh": 2,
        "current": {
          "text": "All",
          "value": "$__all",
          "selected": true
        }
      },
      {
        "type": "query",
        "name": "template",
        "label": "Template",
        "datasource": {
          "type": "grafana-clickhouse-datasource",
          "uid": "${datasource}"
        },
        "query": {
          "refId": "var",
          "rawSql": "SELECT DISTINCT request_template FROM alo.alo_raw WHERE $__timeFilter(timestamp) ORDER BY 1 LIMIT 1000",
          "editorType": "sql"
        },
        "includeAll": true,
        "allValue": "*",
        "multi": true,
        "sort": 1,
        "refresh": 2,
        "current": {
          "text": "All",
          "value": "$__all",
          "selected": true
        }
      },
      {
        "type": "adhoc",
        "name": "Filters",
        "datasource": {
          "type": "grafana-clickhouse-datasource",
          "uid": "${datasource}"
        }
      }
    ]
  },
  "annotations": {
    "list": []
  },
  "editable": true
}
